PyBIS-1.6.4.dist-info/DESCRIPTION.rst
PyBIS-1.6.4.dist-info/METADATA
PyBIS-1.6.4.dist-info/RECORD
PyBIS-1.6.4.dist-info/WHEEL
PyBIS-1.6.4.dist-info/metadata.json
PyBIS-1.6.4.dist-info/top_level.txt
pybis/__init__.py
pybis/attachment.py
pybis/attribute.py
pybis/data_set.py
pybis/dataset.py
pybis/definitions.py
pybis/experiment.py
pybis/group.py
pybis/masterdata.py
pybis/material.py
pybis/openbis_object.py
pybis/person.py
pybis/plugin.py
pybis/project.py
pybis/property.py
pybis/pybis.py
pybis/role_assignment.py
pybis/sample.py
pybis/semantic_annotation.py
pybis/space.py
pybis/tag.py
pybis/things.py
pybis/utils.py
pybis/vocabulary.py
