Metadata-Version: 2.0
Name: PyBIS
Version: 1.6.4
Summary: openBIS connection and interaction, optimized for using with Jupyter
Home-page: https://sissource.ethz.ch/sispub/pybis/
Author: Swen Vermeul |  ID SIS | ETH Zürich
Author-email: swen@ethz.ch
License: BSD
Platform: UNKNOWN
Requires-Python: >=3.3
Requires-Dist: click
Requires-Dist: datetime
Requires-Dist: pandas
Requires-Dist: pytest
Requires-Dist: requests
Requires-Dist: tabulate
Requires-Dist: texttable
